MANIFEST.in
requirements.txt
setup.py
src/MurmurHash3.c
src/MurmurHash3.h
src/_pydmc.c
src/_pydmc.pyx
src/pydmc.py
src/pydmc.egg-info/PKG-INFO
src/pydmc.egg-info/SOURCES.txt
src/pydmc.egg-info/dependency_links.txt
src/pydmc.egg-info/not-zip-safe
src/pydmc.egg-info/top_level.txt
tests/test_dmc.py
tests/test_mhash.py