Metadata-Version: 1.0
Name: pydmc
Version: 0.3
Summary: A high performance python direct-memory-cache type thing.
Home-page: http://github.com/jhgg/pydmc
Author: Jake Heinz
Author-email: me@jh.gg
License: MIT License
Platform: UNKNOWN
